{"electionCandidates":[{"candidates":[{"alternateCandidates":null,"effectiveCandidates":["Artur José Araújo de Arruda Ponte"],"mandates":0,"party":"CDS-PP","presidents":0},{"alternateCandidates":null,"effectiveCandidates":["Antero Jerónimo Moniz Arruda Quental"],"mandates":0,"party":"PCP-PEV","presidents":0},{"alternateCandidates":null,"effectiveCandidates":["Filomeno dos Anjos da Silva Gouveia"],"mandates":3,"party":"PPD/PSD","presidents":0},{"alternateCandidates":null,"effectiveCandidates":["Ricardo José Moniz da Silva"],"mandates":4,"party":"PS","presidents":1}],"parentTerritoryName":"Açores","territoryKey":"LOCAL-420500","territoryName":"Ribeira Grande"},{"candidates":[{"alternateCandidates":null,"effectiveCandidates":["João Manuel Pacheco Furtado"],"mandates":0,"party":"CDS-PP","presidents":0},{"alternateCandidates":null,"effectiveCandidates":["Juvenálio dos Santos da Ponte"],"mandates":0,"party":"PCP-PEV","presidents":0},{"alternateCandidates":null,"effectiveCandidates":["Rui António Dias da Câmara de Carvalho e Melo"],"mandates":2,"party":"PPD/PSD","presidents":0},{"alternateCandidates":null,"effectiveCandidates":["António Fernando Raposo Cordeiro"],"mandates":3,"party":"PS","presidents":1}],"parentTerritoryName":"Açores","territoryKey":"LOCAL-420600","territoryName":"Vila Franca do Campo"},{"candidates":[{"alternateCandidates":null,"effectiveCandidates":["Orlando Manuel Labrusco Félix Guerreiro"],"mandates":0,"party":"B.E.","presidents":0},{"alternateCandidates":null,"effectiveCandidates":["Artur Manuel Leal Lima"],"mandates":1,"party":"CDS-PP","presidents":0},{"alternateCandidates":null,"effectiveCandidates":["António Gabriel Botelho da Fonseca"],"mandates":0,"party":"PCP-PEV","presidents":0},{"alternateCandidates":null,"effectiveCandidates":["António Lima Cardoso Ventura"],"mandates":3,"party":"PPD/PSD","presidents":0},{"alternateCandidates":null,"effectiveCandidates":["Andreia Martins Cardoso da Costa"],"mandates":3,"party":"PS","presidents":1}],"parentTerritoryName":"Açores","territoryKey":"LOCAL-430100","territoryName":"Angra do Heroísmo"},{"candidates":[{"alternateCandidates":null,"effectiveCandidates":["Paulo José Maio Sousa Mendes"],"mandates":0,"party":"B.E.","presidents":0},{"alternateCandidates":null,"effectiveCandidates":["Pedro Gabriel Correia Nunes Teixeira Pinto"],"mandates":0,"party":"CDS-PP","presidents":0},{"alternateCandidates":null,"effectiveCandidates":["Berto Graciliano da Almeida Cabral"],"mandates":2,"party":"PPD/PSD","presidents":0},{"alternateCandidates":null,"effectiveCandidates":["Roberto Lúcio Silva Pereira Monteiro"],"mandates":5,"party":"PS","presidents":1}],"parentTerritoryName":"Açores","territoryKey":"LOCAL-430200","territoryName":"Vila da Praia da Vitória"},{"candidates":[{"alternateCandidates":null,"effectiveCandidates":["José Ramos de Aguiar"],"mandates":2,"party":"PPD/PSD","presidents":0},{"alternateCandidates":null,"effectiveCandidates":["Manuel Avelar Cunha Santos"],"mandates":3,"party":"PS","presidents":1}],"parentTerritoryName":"Açores","territoryKey":"LOCAL-440100","territoryName":"Santa Cruz da Graciosa"},{"candidates":[{"alternateCandidates":null,"effectiveCandidates":["Aires António Fagundes Reis"],"mandates":3,"party":"PPD/PSD","presidents":1},{"alternateCandidates":null,"effectiveCandidates":["Rogério Paulo Lopes Soares Veiros"],"mandates":2,"party":"PS","presidents":0}],"parentTerritoryName":"Açores","territoryKey":"LOCAL-450100","territoryName":"Calheta (R.A.A.)"},{"candidates":[{"alternateCandidates":null,"effectiveCandidates":["António Fernando Cardoso"],"mandates":0,"party":"B.E.","presidents":0},{"alternateCandidates":null,"effectiveCandidates":["Vítor Manuel Assunção Bernardes"],"mandates":0,"party":"CDS-PP","presidents":0},{"alternateCandidates":null,"effectiveCandidates":["António José Bettencourt da Silveira"],"mandates":2,"party":"PPD/PSD","presidents":0},{"alternateCandidates":null,"effectiveCandidates":["Manuel Soares da Silveira"],"mandates":3,"party":"PS","presidents":1}],"parentTerritoryName":"Açores","territoryKey":"LOCAL-450200","territoryName":"Velas"},{"candidates":[{"alternateCandidates":null,"effectiveCandidates":["Sara Maria Alves da Rosa Santos"],"mandates":2,"party":"PPD/PSD","presidents":0},{"alternateCandidates":null,"effectiveCandidates":["Roberto Manuel Medeiros da Silva"],"mandates":3,"party":"PS","presidents":1}],"parentTerritoryName":"Açores","territoryKey":"LOCAL-460100","territoryName":"Lajes do Pico"},{"candidates":[{"alternateCandidates":null,"effectiveCandidates":["Elisabete da Piedade Alves"],"mandates":0,"party":"PCP-PEV","presidents":0},{"alternateCandidates":null,"effectiveCandidates":["Jorge Manuel Pereira Rodrigues"],"mandates":4,"party":"PPD/PSD","presidents":1},{"alternateCandidates":null,"effectiveCandidates":["Hernani Hélio Jorge"],"mandates":1,"party":"PS","presidents":0}],"parentTerritoryName":"Açores","territoryKey":"LOCAL-460200","territoryName":"Madalena"},{"candidates":[{"alternateCandidates":null,"effectiveCandidates":["Rosa Maria da Silva Vieira"],"mandates":0,"party":"CDS-PP","presidents":0},{"alternateCandidates":null,"effectiveCandidates":["José Manuel Bettencourt Ávila"],"mandates":0,"party":"PCP-PEV","presidents":0},{"alternateCandidates":null,"effectiveCandidates":["Luís Filipe Ramos Macedo da Silva"],"mandates":3,"party":"PPD/PSD","presidents":1},{"alternateCandidates":null,"effectiveCandidates":["Paulo Jaime Terra Goulart"],"mandates":2,"party":"PS","presidents":0}],"parentTerritoryName":"Açores","territoryKey":"LOCAL-460300","territoryName":"São Roque do Pico"},{"candidates":[{"alternateCandidates":null,"effectiveCandidates":["Maria José Ferreira da Silva"],"mandates":0,"party":"B.E.","presidents":0},{"alternateCandidates":null,"effectiveCandidates":["Alexandre Agostinho Martins de Carvalho"],"mandates":0,"party":"CDS-PP","presidents":0},{"alternateCandidates":null,"effectiveCandidates":["José Eduardo Bicudo Decq Mota"],"mandates":0,"party":"PCP-PEV","presidents":0},{"alternateCandidates":null,"effectiveCandidates":["Paulo Jorge Peixinho de Oliveira"],"mandates":3,"party":"PPD/PSD","presidents":0},{"alternateCandidates":null,"effectiveCandidates":["João Fernando Brum de Azevedo e Castro"],"mandates":4,"party":"PS","presidents":1}],"parentTerritoryName":"Açores","territoryKey":"LOCAL-470100","territoryName":"Horta"},{"candidates":[{"alternateCandidates":null,"effectiveCandidates":["João António Vieira Lourenço"],"mandates":3,"party":"PPD/PSD","presidents":1},{"alternateCandidates":null,"effectiveCandidates":["Luís Carlos Martins Maciel"],"mandates":2,"party":"PS","presidents":0}],"parentTerritoryName":"Açores","territoryKey":"LOCAL-480100","territoryName":"Lajes das Flores"},{"candidates":[{"alternateCandidates":null,"effectiveCandidates":["Rosa Margarida Ribeiro Cravinho"],"mandates":0,"party":"CDS-PP","presidents":0},{"alternateCandidates":null,"effectiveCandidates":["João Paulo Valadão Corvelo"],"mandates":0,"party":"PCP-PEV","presidents":0},{"alternateCandidates":null,"effectiveCandidates":["Hélio Fernando Miranda Ramos"],"mandates":1,"party":"PPD/PSD","presidents":0},{"alternateCandidates":null,"effectiveCandidates":["Manuel Alberto da Silva Pereira"],"mandates":4,"party":"PS","presidents":1}],"parentTerritoryName":"Açores","territoryKey":"LOCAL-480200","territoryName":"Santa Cruz das Flores"},{"candidates":[{"alternateCandidates":null,"effectiveCandidates":["Deolinda Rosa Machado Vieira Estevão"],"mandates":1,"party":"PPD/PSD","presidents":0},{"alternateCandidates":null,"effectiveCandidates":["Manuel das Pedras Rita"],"mandates":4,"party":"PS","presidents":1}],"parentTerritoryName":"Açores","territoryKey":"LOCAL-490100","territoryName":"Corvo"}],"numberOfPages":27,"page":27,"parties":[{"acronym":"B.E.","name":"Bloco de Esquerda"},{"acronym":"CDS-PP","name":"CDS - Partido Popular"},{"acronym":"CDS-PP.MPT","name":"Sangue Novo Pela Nossa Terra"},{"acronym":"CDS-PP.PPM","name":"JUNTOS POR FORNOS"},{"acronym":"I","name":"LIFA - Lista Independente da Freguesia de Águeda"},{"acronym":"II","name":"LIAB - Lista Independente de Aguada de Baixo"},{"acronym":"III","name":"JPP- Juntos por Pessegueiro"},{"acronym":"IV","name":"LIE - Lista Independente da Freguesia de Espinhel"},{"acronym":"MEP","name":"Movimento Esperança Portugal"},{"acronym":"MMS","name":"Movimento Mérito e Sociedade"},{"acronym":"MPT","name":"Partido da Terra"},{"acronym":"P.N.R.","name":"Partido Nacional Renovador"},{"acronym":"PCP-PEV","name":"CDU - Coligação Democrática Unitária"},{"acronym":"PCTP/MRPP","name":"Partido Comunista dos Trabalhadores Portugueses"},{"acronym":"PND","name":"Nova Democracia"},{"acronym":"PPD/PSD","name":"Partido Social Democrata"},{"acronym":"PPD/PSD.CDS-PP","name":"Juntos por Aveiro"},{"acronym":"PPD/PSD.CDS-PP.MPT","name":"Todos por Penamacor"},{"acronym":"PPD/PSD.CDS-PP.MPT.PPM","name":"FARO ESTÁ PRIMEIRO"},{"acronym":"PPD/PSD.CDS-PP.PPM","name":"Aliança Democrática"},{"acronym":"PPD/PSD.CDS-PP.PPM.MPT","name":"Pela Nossa Terra"},{"acronym":"PPM","name":"Partido Popular Monárquico"},{"acronym":"PS","name":"Partido Socialista"},{"acronym":"PTP","name":"Partido Trabalhista Português"},{"acronym":"V","name":"LIP - Lista Independente de Préstimo"},{"acronym":"VI","name":"LP - Lista Progresso"},{"acronym":"VIII","name":"LICE- Lista de Independentes de Couto de Esteves"},{"acronym":"X","name":"IPLV-Independentes Paradela Livre Vencerá"},{"acronym":"XI","name":"ISELV-Independentes Silva Escura Vencerá"},{"acronym":"XII","name":"Alfredo Rocha Independente por Guetim"},{"acronym":"XIII","name":"IDLV-Independentes Dornelas LIvre Vencerá"},{"acronym":"XIV","name":"Unidos por Nariz"},{"acronym":"XIX","name":"Unidos pela Amareleja pela Mudança-UPAPM"},{"acronym":"XV","name":"Mais e melhor por Garvão"},{"acronym":"XVI","name":"Lista Independente por Silvalde"},{"acronym":"XVII","name":"JPNF-Juntos pela Nossa Freguesia"},{"acronym":"XVIII","name":"Independentes de Paramos"}]}